playlistparser/__init__.py
playlistparser/track.py
playlistparser/utils.py
playlistparser/parsers/engine.py
playlistparser/parsers/rekordbox.py
playlistparser/parsers/serato.py
playlistparser/parsers/traktor.py
playlistparser/parsers/virtualdj.py
playlistparser-3.0.0b10.dist-info/METADATA
playlistparser-3.0.0b10.dist-info/WHEEL
playlistparser-3.0.0b10.dist-info/licenses/LICENSE.md
playlistparser-3.0.0b10.dist-info/RECORD
