Metadata-Version: 2.3
Name: playlistparser
Version: 3.0.0b10
Summary: Tool for parsing DJ software playlists
Project-URL: Changelog, https://github.com/slipmatio/playlistparser/blob/main/CHANGES.md
Project-URL: Bluesky, https://bsky.app/profile/uninen.net
Project-URL: Source, https://github.com/slipmatio/playlistparser
Project-URL: Twitter, https://twitter.com/uninen
Author-email: Ville Säävuori <ville@unessa.net>
License: AGPL-3.0-or-later
Classifier: Development Status :: 4 - Beta
Classifier: Intended Audience :: Developers
Classifier: Programming Language :: Python :: 3
Classifier: Programming Language :: Python :: 3.11
Classifier: Programming Language :: Python :: 3.12
Classifier: Programming Language :: Python :: 3.13
